spanreed/__init__.py
spanreed/commands.py
spanreed/const.py
spanreed/consumer.py
spanreed/exceptions.py
spanreed/models.py
spanreed/publisher.py
spanreed/task_manager.py
spanreed/backend/__init__.py
spanreed/backend/redis.py
spanreed/conf/__init__.py
spanreed/management/commands/__init__.py
spanreed/management/commands/spanreed_worker.py
spanreed/testing/__init__.py
spanreed/testing/pytest_plugin.py
spanreed-0.2.dist-info/licenses/LICENSE
spanreed-0.2.dist-info/METADATA
spanreed-0.2.dist-info/WHEEL
spanreed-0.2.dist-info/entry_points.txt
spanreed-0.2.dist-info/top_level.txt
spanreed-0.2.dist-info/RECORD
