Metadata-Version: 2.4
Name: spanreed
Version: 0.2
Author-email: Marcin Bachry <hegel666@gmail.com>
Requires-Python: >=3.12
License-File: LICENSE
Requires-Dist: pydantic
Requires-Dist: pydantic-settings
Requires-Dist: walrus
Provides-Extra: dev
Requires-Dist: django; extra == "dev"
Requires-Dist: factory-boy; extra == "dev"
Requires-Dist: pytest; extra == "dev"
Requires-Dist: pytest-cov; extra == "dev"
Requires-Dist: pytest-env; extra == "dev"
Requires-Dist: pytest-redis; extra == "dev"
Requires-Dist: tox-factor; extra == "dev"
Requires-Dist: tox-pyenv; extra == "dev"
Dynamic: license-file
